.gitignore
.travis.yml
CHANGES.txt
LICENSE.txt
README.rst
setup.cfg
setup.py
bin/nepho_completer
ci/requirements.txt
doc/Nepho_Object_Model.graffle
doc/Nepho_Object_Model.png
nepho/__init__.py
nepho.egg-info/PKG-INFO
nepho.egg-info/SOURCES.txt
nepho.egg-info/dependency_links.txt
nepho.egg-info/entry_points.txt
nepho.egg-info/requires.txt
nepho.egg-info/top_level.txt
nepho/cli/__init__.py
nepho/cli/base.py
nepho/cli/blueprint.py
nepho/cli/bootstrap.py
nepho/cli/cloudlet.py
nepho/cli/hooks.py
nepho/cli/parameter.py
nepho/cli/scope.py
nepho/cli/stack.py
nepho/core/__init__.py
nepho/core/blueprint.py
nepho/core/cloudlet.py
nepho/core/common.py
nepho/core/parameter.py
nepho/core/provider.py
nepho/core/provider_factory.py
nepho/core/scenario.py
nepho/core/stack.py
nepho/providers/__init__.py
nepho/providers/aws_provider.py
nepho/providers/vagrant_provider.py
tests/README.md
tests/TEMPLATE_test.py
tests/__init__.py
tests/basic_test.py
tests/blueprint_test.py
tests/cloudlet_test.py
tests/parameter_test.py
tests/scope_test.py
tests/stack_test.py