Metadata-Version: 1.0
Name: nepho
Version: 1.2.3
Summary: Simplified cloud orchestration tool for constructing virtual data centers
Home-page: http://github.com/huit/nepho
Author: Harvard University Information Technology
Author-email: ithelp@harvard.edu
License: LICENSE.txt
Platform: UNKNOWN
